djangocms_darksky_api/__init__.py
djangocms_darksky_api/apps.py
djangocms_darksky_api/cms_plugins.py
djangocms_darksky_api/models.py
djangocms_darksky_api/tests.py
djangocms_darksky_api/views.py
djangocms_darksky_api/conf/settings.py
djangocms_darksky_api/locale/fr/LC_MESSAGES/django.mo
djangocms_darksky_api/locale/fr/LC_MESSAGES/django.po
djangocms_darksky_api/migrations/0001_initial.py
djangocms_darksky_api/migrations/0002_darkskyapi_template.py
djangocms_darksky_api/migrations/0003_auto_20200113_1036.py
djangocms_darksky_api/migrations/0004_auto_20200114_1427.py
djangocms_darksky_api/migrations/0005_auto_20200114_1430.py
djangocms_darksky_api/migrations/__init__.py
djangocms_darksky_api/templates/darkskyapi_full.html
djangocms_darksky_api/templates/darkskyapi_light.html
djangocms_darksky_api/templatetags/__init__.py
djangocms_darksky_api/templatetags/get_datetime_from_timestamp.py
djangocms_darksky_api-0.0.6.dist-info/LICENSE
djangocms_darksky_api-0.0.6.dist-info/METADATA
djangocms_darksky_api-0.0.6.dist-info/WHEEL
djangocms_darksky_api-0.0.6.dist-info/top_level.txt
djangocms_darksky_api-0.0.6.dist-info/RECORD
