Metadata-Version: 2.1
Name: djangocms-darksky-api
Version: 0.0.6
Summary: This djangocms plugin allows you to add a weather indicator on your pages, using the Dark Sky API (https://darksky.net/dev/docs).
Home-page: https://github.com/kapt-labs/djangocms-darksky-api
Author: Dev Kapt
Author-email: dev@kapt.mobi
License: UNKNOWN
Platform: UNKNOWN
Classifier: Environment :: Web Environment
Classifier: Framework :: Django
Classifier: Intended Audience :: Developers
Classifier: License :: OSI Approved :: GNU General Public License v3 (GPLv3)
Classifier: Programming Language :: Python
Classifier: Programming Language :: Python :: 3
Classifier: Programming Language :: Python :: 3 :: Only
Classifier: Programming Language :: Python :: 3.7
Classifier: Programming Language :: Python :: 3.8
Classifier: Topic :: Internet :: WWW/HTTP
Classifier: Topic :: Internet :: WWW/HTTP :: Dynamic Content
Requires-Dist: django (<3.0)
Requires-Dist: django-cms
Requires-Dist: requests
